RuheChengweiYimingHeike/README.md
RuheChengweiYimingHeike/__init__.py
RuheChengweiYimingHeike/__main__.py
RuheChengweiYimingHeike/file.epub
RuheChengweiYimingHeike/index.html
RuheChengweiYimingHeike/css/__init__.py
RuheChengweiYimingHeike/css/annotations.css
RuheChengweiYimingHeike/css/main.css
RuheChengweiYimingHeike/css/normalize.css
RuheChengweiYimingHeike/css/popup.css
RuheChengweiYimingHeike/font/__init__.py
RuheChengweiYimingHeike/font/fontello.eot
RuheChengweiYimingHeike/font/fontello.svg
RuheChengweiYimingHeike/font/fontello.ttf
RuheChengweiYimingHeike/font/fontello.woff
RuheChengweiYimingHeike/img/__init__.py
RuheChengweiYimingHeike/img/annotator-glyph-sprite.png
RuheChengweiYimingHeike/img/annotator-icon-sprite.png
RuheChengweiYimingHeike/img/apple-touch-icon.png
RuheChengweiYimingHeike/img/cancelfullscreen.png
RuheChengweiYimingHeike/img/close.png
RuheChengweiYimingHeike/img/fullscreen.png
RuheChengweiYimingHeike/img/loader.gif
RuheChengweiYimingHeike/img/menu-icon.png
RuheChengweiYimingHeike/img/save.png
RuheChengweiYimingHeike/img/saved.png
RuheChengweiYimingHeike/img/settings-s.png
RuheChengweiYimingHeike/img/settings.png
RuheChengweiYimingHeike/img/star.png
RuheChengweiYimingHeike/js/__init__.py
RuheChengweiYimingHeike/js/epub.js
RuheChengweiYimingHeike/js/epub.min.js
RuheChengweiYimingHeike/js/epub.min.map
RuheChengweiYimingHeike/js/hooks.min.js
RuheChengweiYimingHeike/js/hooks.min.map
RuheChengweiYimingHeike/js/reader.js
RuheChengweiYimingHeike/js/reader.js.map
RuheChengweiYimingHeike/js/reader.min.js
RuheChengweiYimingHeike/js/reader.min.map
RuheChengweiYimingHeike/js/hooks/__init__.py
RuheChengweiYimingHeike/js/hooks/extensions/__init__.py
RuheChengweiYimingHeike/js/hooks/extensions/highlight.js
RuheChengweiYimingHeike/js/libs/__init__.py
RuheChengweiYimingHeike/js/libs/jquery.min.js
RuheChengweiYimingHeike/js/libs/localforage.min.js
RuheChengweiYimingHeike/js/libs/screenfull.js
RuheChengweiYimingHeike/js/libs/screenfull.min.js
ruhe_chengwei_yiming_heike-2024.3.1.0.dist-info/METADATA
ruhe_chengwei_yiming_heike-2024.3.1.0.dist-info/WHEEL
ruhe_chengwei_yiming_heike-2024.3.1.0.dist-info/entry_points.txt
ruhe_chengwei_yiming_heike-2024.3.1.0.dist-info/top_level.txt
ruhe_chengwei_yiming_heike-2024.3.1.0.dist-info/RECORD
